sio_asyncapi/__init__.py
sio_asyncapi/application.py
sio_asyncapi/asyncapi/docs.py
sio_asyncapi/asyncapi/models/__init__.py
sio_asyncapi/asyncapi/models/amqp1_bindings.py
sio_asyncapi/asyncapi/models/amqp_bindings.py
sio_asyncapi/asyncapi/models/anypoint_mq_bindings.py
sio_asyncapi/asyncapi/models/async_api.py
sio_asyncapi/asyncapi/models/async_api_base.py
sio_asyncapi/asyncapi/models/channel.py
sio_asyncapi/asyncapi/models/channel_bindings.py
sio_asyncapi/asyncapi/models/components.py
sio_asyncapi/asyncapi/models/contact.py
sio_asyncapi/asyncapi/models/correlation_id.py
sio_asyncapi/asyncapi/models/external_documentation.py
sio_asyncapi/asyncapi/models/http_bindings.py
sio_asyncapi/asyncapi/models/ibm_mq_bindings.py
sio_asyncapi/asyncapi/models/info.py
sio_asyncapi/asyncapi/models/jms_bindings.py
sio_asyncapi/asyncapi/models/json_schema.py
sio_asyncapi/asyncapi/models/kafka_bindings.py
sio_asyncapi/asyncapi/models/license.py
sio_asyncapi/asyncapi/models/mercure_bindings.py
sio_asyncapi/asyncapi/models/message.py
sio_asyncapi/asyncapi/models/message_bindings.py
sio_asyncapi/asyncapi/models/message_example.py
sio_asyncapi/asyncapi/models/message_trait.py
sio_asyncapi/asyncapi/models/mqtt5_bindings.py
sio_asyncapi/asyncapi/models/mqtt_bindings.py
sio_asyncapi/asyncapi/models/nats_bindings.py
sio_asyncapi/asyncapi/models/oauth_flows.py
sio_asyncapi/asyncapi/models/operation.py
sio_asyncapi/asyncapi/models/operation_bindings.py
sio_asyncapi/asyncapi/models/operation_trait.py
sio_asyncapi/asyncapi/models/parameter.py
sio_asyncapi/asyncapi/models/redis_bindings.py
sio_asyncapi/asyncapi/models/reference.py
sio_asyncapi/asyncapi/models/schema.py
sio_asyncapi/asyncapi/models/security_requirement.py
sio_asyncapi/asyncapi/models/security_scheme.py
sio_asyncapi/asyncapi/models/server.py
sio_asyncapi/asyncapi/models/server_bindings.py
sio_asyncapi/asyncapi/models/server_variable.py
sio_asyncapi/asyncapi/models/sns_bindings.py
sio_asyncapi/asyncapi/models/solace_bindings.py
sio_asyncapi-0.3.0.dist-info/METADATA
sio_asyncapi-0.3.0.dist-info/WHEEL
sio_asyncapi-0.3.0.dist-info/RECORD
