Metadata-Version: 2.1
Name: sio-asyncapi
Version: 0.3.0
Summary: Flask SocketIO with auto-generate Asyncapi documentation
License: MIT
Author: Daler Rahimov
Author-email: daler.edu@gmail.com
Requires-Python: >=3.8.10,<4.0.0
Classifier: License :: OSI Approved :: MIT License
Classifier: Programming Language :: Python :: 3
Classifier: Programming Language :: Python :: 3.9
Classifier: Programming Language :: Python :: 3.10
Classifier: Programming Language :: Python :: 3.11
Requires-Dist: flask-socketio (>=5.3.2,<6.0.0)
Requires-Dist: loguru (>=0.6.0,<0.7.0)
Requires-Dist: pydantic[email] (>=1.10.4,<2.0.0)
Requires-Dist: python-engineio (>=4.3.4,<5.0.0)
Requires-Dist: pyyaml (>=6.0,<7.0)
